nomad_docs/__init__.py
nomad_docs/metainfo.py
nomad_docs/pydantic.py
nomad_docs-0.1.3.dist-info/WHEEL
nomad_docs-0.1.3.dist-info/METADATA
nomad_docs-0.1.3.dist-info/RECORD
