Metadata-Version: 2.3
Name: nomad-docs
Version: 0.1.3
Summary: Add your description here
Author: Ahmed Ilyas
Author-email: Ahmed Ilyas <ahmed.n.ilyas@gmail.com>
Requires-Dist: mkdocs-click
Requires-Dist: mkdocs-git-revision-date-localized-plugin
Requires-Dist: mkdocs-glightbox
Requires-Dist: mkdocs-macros-plugin
Requires-Dist: mkdocs-material-extensions
Requires-Dist: mkdocs-material
Requires-Dist: mkdocs-redirects
Requires-Dist: mkdocs
Requires-Dist: nomad-lab[infrastructure]>=1.3.16.dev238
Requires-Dist: pydantic>=2.0
Requires-Python: >=3.10
